{
  "Code": "Page_APPLICATIONS",
  "Title": "Applications",
  "FormJson": "{\"settings\":{\"visible\":true,\"isHidden\":false,\"readOnly\":false,\"disable\":false,\"showLabelCaption\":false,\"labelIconType\":1,\"controlIcon\":{\"name\":\"\",\"type\":2,\"materialsShape\":\"rounded\",\"category\":3,\"customType\":1,\"position\":1,\"color\":\"var(--t-text-color)\",\"fontSize\":\"16px\",\"flipIconOnRTL\":false},\"menuPosition\":\"left\",\"tooltipPosition\":\"top\",\"tooltipArrowPosition\":\"center\",\"tooltipIcon\":\"\",\"showAdvancedBorderSettings\":false,\"showAdvancedRadiusSettings\":false,\"eventActionList\":[],\"overflow\":\"\",\"enableWidthSize\":false,\"enableHeightSize\":false,\"enableMaxWidthSize\":false,\"enableMaxHeightSize\":false,\"enableMinWidthSize\":false,\"enableMinHeightSize\":false,\"widthSizeUnit\":\"px\",\"heightSizeUnit\":\"px\",\"maxWidthSizeUnit\":\"px\",\"maxHeightSizeUnit\":\"px\",\"minWidthSizeUnit\":\"px\",\"minHeightSizeUnit\":\"px\",\"gapSize\":\"2\",\"hideDesignBackground\":false,\"isSortableOnly\":false,\"controlValue\":\"\",\"label\":{\"style\":{\"textAlign\":\"start\",\"widgetAlignSelf\":\"default\",\"borderStyle\":\"Solid\",\"borderRadius\":\"5\",\"borderWidth\":\"0\",\"borderLeftColor\":{\"value\":\"\",\"expression\":\"\"},\"color\":\"var(--t-text-color)\",\"fontSize\":\"16px\",\"fontFamily\":\"Gadugi\",\"fontWeight\":\"400\",\"fontStyle\":\"normal\",\"textDecoration\":\"normal\",\"backgroundRepeat\":\"no-repeat\",\"backgroundAttachment\":\"Scroll\",\"backgroundPosition\":\"center center\",\"backgroundSizeType\":\"Contain\",\"selectedImages\":[],\"opacity\":\"1\",\"heightSizingType\":\"FitToContent\",\"widthSizingType\":\"FitToContainer\",\"dimensions\":{\"width\":{\"value\":0,\"unit\":\"px\"},\"height\":{\"value\":100,\"unit\":\"px\"}},\"minDimention\":{\"width\":{\"value\":0,\"unit\":\"px\"},\"height\":{\"value\":0,\"unit\":\"px\"}},\"maxDimention\":{\"width\":{\"value\":0,\"unit\":\"px\"},\"height\":{\"value\":0,\"unit\":\"px\"}},\"minWidthActive\":false,\"maxWidthActive\":false,\"minHeightActive\":false,\"maxHeightActive\":false,\"canvasDimension\":{\"width\":\"unset\",\"height\":\"unset\"},\"widgetWidth\":\"fit-container\",\"widgetHeight\":\"fit-content\",\"orientation\":\"Vertical\",\"labelOrientationAlignment\":\"\",\"isHideOnMobile\":false,\"isHideOnTablet\":false,\"isHideOnDesktop\":false,\"shadowColor\":\"#000000\",\"elevation\":0,\"IOSShadow\":{\"shadowColor\":\"#000000\",\"shadowOffset\":{\"width\":0,\"height\":0},\"shadowOpacity\":0,\"shadowRadius\":0},\"margin\":{\"type\":{\"value\":0,\"unit\":\"px\"},\"top\":{\"value\":0,\"unit\":\"px\"},\"bottom\":{\"value\":0,\"unit\":\"px\"},\"left\":{\"value\":0,\"unit\":\"px\"},\"right\":{\"value\":0,\"unit\":\"px\"}},\"padding\":{\"type\":{\"value\":5,\"unit\":\"px\"},\"top\":{\"value\":0,\"unit\":\"px\"},\"bottom\":{\"value\":0,\"unit\":\"px\"},\"left\":{\"value\":0,\"unit\":\"px\"},\"right\":{\"value\":0,\"unit\":\"px\"}},\"backgroundHeight\":{\"value\":0,\"unit\":\"px\"},\"backgroundWidth\":{\"value\":0,\"unit\":\"px\"}},\"cutoffStyle\":{\"isMaxCharacterAllowed\":false,\"noMaxCharacterAllowed\":50,\"cutoffType\":null,\"showMoreCaption\":null,\"showLessCaption\":null},\"text\":\"Page_APPLICATIONS\"},\"style\":{\"textAlign\":\"start\",\"widgetAlignSelf\":\"default\",\"borderStyle\":\"Solid\",\"borderRadius\":\"5\",\"borderWidth\":\"0\",\"borderLeftColor\":{\"value\":\"\",\"expression\":\"\"},\"color\":\"var(--t-text-color)\",\"fontSize\":\"16px\",\"fontFamily\":\"Gadugi\",\"fontWeight\":\"400\",\"fontStyle\":\"normal\",\"textDecoration\":\"normal\",\"backgroundRepeat\":\"no-repeat\",\"backgroundAttachment\":\"Scroll\",\"backgroundPosition\":\"center center\",\"backgroundSizeType\":\"Contain\",\"selectedImages\":[],\"opacity\":\"1\",\"heightSizingType\":\"FitToContent\",\"widthSizingType\":\"FitToContainer\",\"dimensions\":{\"width\":{\"value\":0,\"unit\":\"px\"},\"height\":{\"value\":100,\"unit\":\"px\"}},\"minDimention\":{\"width\":{\"value\":0,\"unit\":\"px\"},\"height\":{\"value\":0,\"unit\":\"px\"}},\"maxDimention\":{\"width\":{\"value\":0,\"unit\":\"px\"},\"height\":{\"value\":0,\"unit\":\"px\"}},\"minWidthActive\":false,\"maxWidthActive\":false,\"minHeightActive\":false,\"maxHeightActive\":false,\"canvasDimension\":{\"width\":\"unset\",\"height\":\"unset\"},\"widgetWidth\":\"fit-container\",\"widgetHeight\":\"fit-content\",\"orientation\":\"Inherit\",\"labelOrientationAlignment\":\"\",\"isHideOnMobile\":false,\"isHideOnTablet\":false,\"isHideOnDesktop\":false,\"shadowColor\":\"#000000\",\"elevation\":0,\"IOSShadow\":{\"shadowColor\":\"#000000\",\"shadowOffset\":{\"width\":0,\"height\":0},\"shadowOpacity\":0,\"shadowRadius\":0},\"margin\":{\"type\":{\"value\":0,\"unit\":\"px\"},\"top\":{\"value\":0,\"unit\":\"px\"},\"bottom\":{\"value\":0,\"unit\":\"px\"},\"left\":{\"value\":0,\"unit\":\"px\"},\"right\":{\"value\":0,\"unit\":\"px\"}},\"padding\":{\"type\":{\"value\":5,\"unit\":\"px\"},\"top\":{\"value\":0,\"unit\":\"px\"},\"bottom\":{\"value\":0,\"unit\":\"px\"},\"left\":{\"value\":0,\"unit\":\"px\"},\"right\":{\"value\":0,\"unit\":\"px\"}},\"backgroundHeight\":{\"value\":0,\"unit\":\"px\"},\"backgroundWidth\":{\"value\":0,\"unit\":\"px\"}},\"containerStyle\":{\"textAlign\":\"start\",\"widgetAlignSelf\":\"default\",\"borderStyle\":\"Solid\",\"borderRadius\":\"5\",\"borderWidth\":\"0\",\"borderLeftColor\":{\"value\":\"\",\"expression\":\"\"},\"color\":\"var(--t-text-color)\",\"fontSize\":\"16px\",\"fontFamily\":\"Gadugi\",\"fontWeight\":\"400\",\"fontStyle\":\"normal\",\"textDecoration\":\"normal\",\"backgroundRepeat\":\"no-repeat\",\"backgroundAttachment\":\"Scroll\",\"backgroundPosition\":\"center center\",\"backgroundSizeType\":\"Contain\",\"selectedImages\":[],\"opacity\":\"1\",\"heightSizingType\":\"FitToContent\",\"widthSizingType\":\"FitToContainer\",\"dimensions\":{\"width\":{\"value\":0,\"unit\":\"px\"},\"height\":{\"value\":100,\"unit\":\"px\"}},\"minDimention\":{\"width\":{\"value\":0,\"unit\":\"px\"},\"height\":{\"value\":0,\"unit\":\"px\"}},\"maxDimention\":{\"width\":{\"value\":0,\"unit\":\"px\"},\"height\":{\"value\":0,\"unit\":\"px\"}},\"minWidthActive\":false,\"maxWidthActive\":false,\"minHeightActive\":false,\"maxHeightActive\":false,\"canvasDimension\":{\"width\":\"unset\",\"height\":\"unset\"},\"widgetWidth\":\"fit-container\",\"widgetHeight\":\"fit-content\",\"orientation\":\"Inherit\",\"labelOrientationAlignment\":\"\",\"isHideOnMobile\":false,\"isHideOnTablet\":false,\"isHideOnDesktop\":false,\"shadowColor\":\"#000000\",\"elevation\":0,\"IOSShadow\":{\"shadowColor\":\"#000000\",\"shadowOffset\":{\"width\":0,\"height\":0},\"shadowOpacity\":0,\"shadowRadius\":0},\"margin\":{\"type\":{\"value\":0,\"unit\":\"px\"},\"top\":{\"value\":0,\"unit\":\"px\"},\"bottom\":{\"value\":0,\"unit\":\"px\"},\"left\":{\"value\":0,\"unit\":\"px\"},\"right\":{\"value\":0,\"unit\":\"px\"}},\"padding\":{\"type\":{\"value\":5,\"unit\":\"px\"},\"top\":{\"value\":0,\"unit\":\"px\"},\"bottom\":{\"value\":0,\"unit\":\"px\"},\"left\":{\"value\":0,\"unit\":\"px\"},\"right\":{\"value\":0,\"unit\":\"px\"}},\"backgroundHeight\":{\"value\":0,\"unit\":\"px\"},\"backgroundWidth\":{\"value\":0,\"unit\":\"px\"}},\"visibility\":{\"type\":\"Always\"},\"enablement\":{\"type\":\"Always\",\"readonlyStyle\":\"Control\"},\"imageCollectionInfo\":{},\"tooltipStyle\":{\"color\":\"#fff\",\"fontSize\":\"16px\",\"fontStyle\":\"400\",\"backgroundColor\":\"#495057\",\"textDecoration\":\"normal\"},\"pageParameters\":[],\"pageOutputParameters\":[],\"WFForm\":{\"layoutId\":\"00000000-0000-0000-0000-000000000000\",\"anynomousPage\":true,\"isHomePage\":false,\"isMobile\":false,\"isUnauthorizedPage\":false,\"maestroThemeId\":\"00000000-0000-0000-0000-000000000000\",\"mediaCollections\":[],\"navigationIds\":[]},\"selectedOwnModel\":\"\",\"scrollable\":true,\"pageValues\":[],\"isPageScrollable\":true,\"isSetFocusError\":false,\"orientation\":\"vertical\",\"name\":\"Page_APPLICATIONS\",\"refId\":\"d7f0b807-f4d4-41ec-8491-69f6b35996b4\"},\"formJson\":[{\"name\":\"MainPlaceholder\",\"type\":\"Studio\",\"value\":\"\",\"settings\":{\"visible\":true,\"isHidden\":false,\"readOnly\":false,\"disable\":false,\"showLabelCaption\":false,\"labelIconType\":1,\"controlIcon\":{\"name\":\"\",\"type\":2,\"materialsShape\":\"rounded\",\"category\":3,\"customType\":1,\"position\":1,\"color\":\"var(--t-text-color)\",\"fontSize\":\"16px\",\"flipIconOnRTL\":false},\"menuPosition\":\"left\",\"tooltipPosition\":\"top\",\"tooltipArrowPosition\":\"center\",\"tooltipIcon\":\"\",\"showAdvancedBorderSettings\":false,\"showAdvancedRadiusSettings\":false,\"eventActionList\":[],\"overflow\":\"\",\"enableWidthSize\":false,\"enableHeightSize\":false,\"enableMaxWidthSize\":false,\"enableMaxHeightSize\":false,\"enableMinWidthSize\":false,\"enableMinHeightSize\":false,\"widthSizeUnit\":\"px\",\"heightSizeUnit\":\"px\",\"maxWidthSizeUnit\":\"px\",\"maxHeightSizeUnit\":\"px\",\"minWidthSizeUnit\":\"px\",\"minHeightSizeUnit\":\"px\",\"gapSize\":\"2\",\"hideDesignBackground\":false,\"isSortableOnly\":false,\"controlValue\":\"\",\"label\":{\"style\":{\"textAlign\":\"start\",\"widgetAlignSelf\":\"default\",\"borderStyle\":\"Solid\",\"borderRadius\":\"5\",\"borderWidth\":\"0\",\"borderLeftColor\":{\"value\":\"\",\"expression\":\"\"},\"color\":\"var(--t-text-color)\",\"fontSize\":\"16px\",\"fontFamily\":\"Gadugi\",\"fontWeight\":\"400\",\"fontStyle\":\"normal\",\"textDecoration\":\"normal\",\"backgroundRepeat\":\"no-repeat\",\"backgroundAttachment\":\"Scroll\",\"backgroundPosition\":\"center center\",\"backgroundSizeType\":\"Contain\",\"selectedImages\":[],\"opacity\":\"1\",\"heightSizingType\":\"FitToContent\",\"widthSizingType\":\"FitToContainer\",\"dimensions\":{\"width\":{\"value\":0,\"unit\":\"px\"},\"height\":{\"value\":100,\"unit\":\"px\"}},\"minDimention\":{\"width\":{\"value\":0,\"unit\":\"px\"},\"height\":{\"value\":0,\"unit\":\"px\"}},\"maxDimention\":{\"width\":{\"value\":0,\"unit\":\"px\"},\"height\":{\"value\":0,\"unit\":\"px\"}},\"minWidthActive\":false,\"maxWidthActive\":false,\"minHeightActive\":false,\"maxHeightActive\":false,\"canvasDimension\":{\"width\":\"unset\",\"height\":\"unset\"},\"widgetWidth\":\"fit-container\",\"widgetHeight\":\"fit-content\",\"orientation\":\"Inherit\",\"labelOrientationAlignment\":\"\",\"isHideOnMobile\":false,\"isHideOnTablet\":false,\"isHideOnDesktop\":false,\"shadowColor\":\"#000000\",\"elevation\":0,\"IOSShadow\":{\"shadowColor\":\"#000000\",\"shadowOffset\":{\"width\":0,\"height\":0},\"shadowOpacity\":0,\"shadowRadius\":0},\"margin\":{\"type\":{\"value\":0,\"unit\":\"px\"},\"top\":{\"value\":0,\"unit\":\"px\"},\"bottom\":{\"value\":0,\"unit\":\"px\"},\"left\":{\"value\":0,\"unit\":\"px\"},\"right\":{\"value\":0,\"unit\":\"px\"}},\"padding\":{\"type\":{\"value\":5,\"unit\":\"px\"},\"top\":{\"value\":0,\"unit\":\"px\"},\"bottom\":{\"value\":0,\"unit\":\"px\"},\"left\":{\"value\":0,\"unit\":\"px\"},\"right\":{\"value\":0,\"unit\":\"px\"}},\"backgroundHeight\":{\"value\":0,\"unit\":\"px\"},\"backgroundWidth\":{\"value\":0,\"unit\":\"px\"}},\"cutoffStyle\":{\"isMaxCharacterAllowed\":false,\"noMaxCharacterAllowed\":50,\"cutoffType\":null,\"showMoreCaption\":null,\"showLessCaption\":null},\"text\":\"MainPlaceholder\"},\"style\":{\"textAlign\":\"start\",\"widgetAlignSelf\":\"default\",\"borderStyle\":\"Solid\",\"borderRadius\":\"5\",\"borderWidth\":\"0\",\"borderLeftColor\":{\"value\":\"\",\"expression\":\"\"},\"color\":\"var(--t-text-color)\",\"fontSize\":\"16px\",\"fontFamily\":\"Gadugi\",\"fontWeight\":\"400\",\"fontStyle\":\"normal\",\"textDecoration\":\"normal\",\"backgroundRepeat\":\"no-repeat\",\"backgroundAttachment\":\"Scroll\",\"backgroundPosition\":\"center center\",\"backgroundSizeType\":\"Contain\",\"selectedImages\":[],\"opacity\":\"1\",\"heightSizingType\":\"FitToContent\",\"widthSizingType\":\"FitToContainer\",\"dimensions\":{\"width\":{\"value\":0,\"unit\":\"px\"},\"height\":{\"value\":100,\"unit\":\"px\"}},\"minDimention\":{\"width\":{\"value\":0,\"unit\":\"px\"},\"height\":{\"value\":0,\"unit\":\"px\"}},\"maxDimention\":{\"width\":{\"value\":0,\"unit\":\"px\"},\"height\":{\"value\":0,\"unit\":\"px\"}},\"minWidthActive\":false,\"maxWidthActive\":false,\"minHeightActive\":false,\"maxHeightActive\":false,\"canvasDimension\":{\"width\":\"unset\",\"height\":\"unset\"},\"widgetWidth\":\"fit-container\",\"widgetHeight\":\"fit-container\",\"orientation\":\"Inherit\",\"labelOrientationAlignment\":\"\",\"isHideOnMobile\":false,\"isHideOnTablet\":false,\"isHideOnDesktop\":false,\"shadowColor\":\"#000000\",\"elevation\":0,\"IOSShadow\":{\"shadowColor\":\"#000000\",\"shadowOffset\":{\"width\":0,\"height\":0},\"shadowOpacity\":0,\"shadowRadius\":0},\"margin\":{\"type\":{\"value\":0,\"unit\":\"px\"},\"top\":{\"value\":0,\"unit\":\"px\"},\"bottom\":{\"value\":0,\"unit\":\"px\"},\"left\":{\"value\":0,\"unit\":\"px\"},\"right\":{\"value\":0,\"unit\":\"px\"}},\"padding\":{\"type\":{\"value\":0,\"unit\":\"px\"},\"top\":{\"value\":0,\"unit\":\"px\"},\"bottom\":{\"value\":0,\"unit\":\"px\"},\"left\":{\"value\":0,\"unit\":\"px\"},\"right\":{\"value\":0,\"unit\":\"px\"}},\"backgroundHeight\":{\"value\":0,\"unit\":\"px\"},\"backgroundWidth\":{\"value\":0,\"unit\":\"px\"},\"styleClasses\":\"\"},\"containerStyle\":{\"textAlign\":\"start\",\"widgetAlignSelf\":\"default\",\"borderStyle\":\"Solid\",\"borderRadius\":\"5\",\"borderWidth\":\"0\",\"borderLeftColor\":{\"value\":\"\",\"expression\":\"\"},\"color\":\"var(--t-text-color)\",\"fontSize\":\"16px\",\"fontFamily\":\"Gadugi\",\"fontWeight\":\"400\",\"fontStyle\":\"normal\",\"textDecoration\":\"normal\",\"backgroundRepeat\":\"no-repeat\",\"backgroundAttachment\":\"Scroll\",\"backgroundPosition\":\"center center\",\"backgroundSizeType\":\"Contain\",\"selectedImages\":[],\"opacity\":\"1\",\"heightSizingType\":\"FitToContent\",\"widthSizingType\":\"FitToContainer\",\"dimensions\":{\"width\":{\"value\":0,\"unit\":\"px\"},\"height\":{\"value\":100,\"unit\":\"px\"}},\"minDimention\":{\"width\":{\"value\":0,\"unit\":\"px\"},\"height\":{\"value\":0,\"unit\":\"px\"}},\"maxDimention\":{\"width\":{\"value\":0,\"unit\":\"px\"},\"height\":{\"value\":0,\"unit\":\"px\"}},\"minWidthActive\":false,\"maxWidthActive\":false,\"minHeightActive\":false,\"maxHeightActive\":false,\"canvasDimension\":{\"width\":\"unset\",\"height\":\"unset\"},\"widgetWidth\":\"fit-container\",\"widgetHeight\":\"fit-content\",\"orientation\":\"Inherit\",\"labelOrientationAlignment\":\"\",\"isHideOnMobile\":false,\"isHideOnTablet\":false,\"isHideOnDesktop\":false,\"shadowColor\":\"#000000\",\"elevation\":0,\"IOSShadow\":{\"shadowColor\":\"#000000\",\"shadowOffset\":{\"width\":0,\"height\":0},\"shadowOpacity\":0,\"shadowRadius\":0},\"margin\":{\"type\":{\"value\":0,\"unit\":\"px\"},\"top\":{\"value\":0,\"unit\":\"px\"},\"bottom\":{\"value\":0,\"unit\":\"px\"},\"left\":{\"value\":0,\"unit\":\"px\"},\"right\":{\"value\":0,\"unit\":\"px\"}},\"padding\":{\"type\":{\"value\":5,\"unit\":\"px\"},\"top\":{\"value\":0,\"unit\":\"px\"},\"bottom\":{\"value\":0,\"unit\":\"px\"},\"left\":{\"value\":0,\"unit\":\"px\"},\"right\":{\"value\":0,\"unit\":\"px\"}},\"backgroundHeight\":{\"value\":0,\"unit\":\"px\"},\"backgroundWidth\":{\"value\":0,\"unit\":\"px\"}},\"visibility\":{\"type\":\"Always\"},\"enablement\":{\"type\":\"Always\",\"readonlyStyle\":\"Control\"},\"imageCollectionInfo\":{},\"tooltipStyle\":{\"color\":\"#fff\",\"fontSize\":\"16px\",\"fontStyle\":\"400\",\"backgroundColor\":\"#495057\",\"textDecoration\":\"normal\"},\"isMain\":true,\"name\":\"MainPlaceholder\"},\"refId\":\"96c26f4c-64f9-4db9-bcaf-7b8f29a9a088\",\"containers\":[],\"label\":\"\",\"droppable\":true,\"parentRefId\":null,\"index\":null,\"classTypeKey\":\"placeholder\",\"settingsConfig\":[],\"typeName\":\"placeholder\",\"tag\":{\"title\":\"placeholder\"},\"isEnablementChanged\":true,\"children\":[{\"name\":\"MainPlaceholder_container\",\"type\":\"Container\",\"value\":null,\"settings\":{\"visible\":true,\"isHidden\":false,\"readOnly\":false,\"disable\":false,\"showLabelCaption\":true,\"labelIconType\":1,\"controlIcon\":{\"name\":\"\",\"type\":2,\"materialsShape\":\"rounded\",\"category\":3,\"customType\":1,\"position\":1,\"color\":\"var(--t-text-color)\",\"fontSize\":\"16px\",\"flipIconOnRTL\":false},\"menuPosition\":\"left\",\"tooltipPosition\":\"top\",\"tooltipArrowPosition\":\"center\",\"tooltipIcon\":\"\",\"showAdvancedBorderSettings\":false,\"showAdvancedRadiusSettings\":false,\"eventActionList\":[],\"overflow\":\"\",\"enableWidthSize\":false,\"enableHeightSize\":false,\"enableMaxWidthSize\":false,\"enableMaxHeightSize\":false,\"enableMinWidthSize\":false,\"enableMinHeightSize\":false,\"widthSizeUnit\":\"px\",\"heightSizeUnit\":\"px\",\"maxWidthSizeUnit\":\"px\",\"maxHeightSizeUnit\":\"px\",\"minWidthSizeUnit\":\"px\",\"minHeightSizeUnit\":\"px\",\"gapSize\":\"2\",\"hideDesignBackground\":false,\"isSortableOnly\":false,\"controlValue\":\"\",\"label\":{\"style\":{\"textAlign\":\"start\",\"widgetAlignSelf\":\"default\",\"borderStyle\":\"Solid\",\"borderRadius\":\"5\",\"borderWidth\":\"0\",\"borderLeftColor\":{\"value\":\"\",\"expression\":\"\"},\"color\":\"var(--t-text-color)\",\"fontSize\":\"16px\",\"fontFamily\":\"Gadugi\",\"fontWeight\":\"400\",\"fontStyle\":\"normal\",\"textDecoration\":\"normal\",\"backgroundRepeat\":\"no-repeat\",\"backgroundAttachment\":\"Scroll\",\"backgroundPosition\":\"center center\",\"backgroundSizeType\":\"Contain\",\"selectedImages\":[],\"opacity\":\"1\",\"heightSizingType\":\"FitToContent\",\"widthSizingType\":\"FitToContainer\",\"dimensions\":{\"width\":{\"value\":0,\"unit\":\"px\"},\"height\":{\"value\":100,\"unit\":\"px\"}},\"minDimention\":{\"width\":{\"value\":0,\"unit\":\"px\"},\"height\":{\"value\":0,\"unit\":\"px\"}},\"maxDimention\":{\"width\":{\"value\":0,\"unit\":\"px\"},\"height\":{\"value\":0,\"unit\":\"px\"}},\"minWidthActive\":false,\"maxWidthActive\":false,\"minHeightActive\":false,\"maxHeightActive\":false,\"canvasDimension\":{\"width\":\"unset\",\"height\":\"unset\"},\"widgetWidth\":\"fit-container\",\"widgetHeight\":\"fit-content\",\"orientation\":\"Inherit\",\"labelOrientationAlignment\":\"\",\"isHideOnMobile\":false,\"isHideOnTablet\":false,\"isHideOnDesktop\":false,\"shadowColor\":\"#000000\",\"elevation\":0,\"IOSShadow\":{\"shadowColor\":\"#000000\",\"shadowOffset\":{\"width\":0,\"height\":0},\"shadowOpacity\":0,\"shadowRadius\":0},\"margin\":{\"type\":{\"value\":0,\"unit\":\"px\"},\"top\":{\"value\":0,\"unit\":\"px\"},\"bottom\":{\"value\":0,\"unit\":\"px\"},\"left\":{\"value\":0,\"unit\":\"px\"},\"right\":{\"value\":0,\"unit\":\"px\"}},\"padding\":{\"type\":{\"value\":5,\"unit\":\"px\"},\"top\":{\"value\":0,\"unit\":\"px\"},\"bottom\":{\"value\":0,\"unit\":\"px\"},\"left\":{\"value\":0,\"unit\":\"px\"},\"right\":{\"value\":0,\"unit\":\"px\"}},\"backgroundHeight\":{\"value\":0,\"unit\":\"px\"},\"backgroundWidth\":{\"value\":0,\"unit\":\"px\"}},\"cutoffStyle\":{\"isMaxCharacterAllowed\":false,\"noMaxCharacterAllowed\":50,\"cutoffType\":null,\"showMoreCaption\":null,\"showLessCaption\":null}},\"style\":{\"textAlign\":\"start\",\"widgetAlignSelf\":\"default\",\"borderStyle\":\"Solid\",\"borderRadius\":\"var(--t-input-radius)\",\"borderWidth\":\"var(--t-border-width)\",\"borderLeftColor\":{\"value\":\"\",\"expression\":\"\"},\"color\":\"var(--t-text-color)\",\"fontSize\":\"16px\",\"fontFamily\":\"Gadugi\",\"fontWeight\":\"400\",\"fontStyle\":\"normal\",\"textDecoration\":\"normal\",\"backgroundRepeat\":\"no-repeat\",\"backgroundAttachment\":\"Scroll\",\"backgroundPosition\":\"center center\",\"backgroundSizeType\":\"Contain\",\"selectedImages\":[],\"opacity\":\"1\",\"heightSizingType\":\"FitToContent\",\"widthSizingType\":\"FitToContainer\",\"dimensions\":{\"width\":{\"value\":0,\"unit\":\"px\"},\"height\":{\"value\":100,\"unit\":\"px\"}},\"minDimention\":{\"width\":{\"value\":0,\"unit\":\"px\"},\"height\":{\"value\":0,\"unit\":\"px\"}},\"maxDimention\":{\"width\":{\"value\":0,\"unit\":\"px\"},\"height\":{\"value\":0,\"unit\":\"px\"}},\"minWidthActive\":false,\"maxWidthActive\":false,\"minHeightActive\":false,\"maxHeightActive\":false,\"canvasDimension\":{\"width\":\"unset\",\"height\":\"unset\"},\"widgetWidth\":\"fit-container\",\"widgetHeight\":\"fit-container\",\"orientation\":\"Inherit\",\"labelOrientationAlignment\":\"\",\"isHideOnMobile\":false,\"isHideOnTablet\":false,\"isHideOnDesktop\":false,\"shadowColor\":\"#000000\",\"elevation\":0,\"IOSShadow\":{\"shadowColor\":\"#000000\",\"shadowOffset\":{\"width\":0,\"height\":0},\"shadowOpacity\":0,\"shadowRadius\":0},\"margin\":{\"type\":{\"value\":0,\"unit\":\"px\"},\"top\":{\"value\":0,\"unit\":\"px\"},\"bottom\":{\"value\":0,\"unit\":\"px\"},\"left\":{\"value\":0,\"unit\":\"px\"},\"right\":{\"value\":0,\"unit\":\"px\"}},\"padding\":{\"type\":{\"value\":5,\"unit\":\"px\"},\"top\":{\"value\":0,\"unit\":\"px\"},\"bottom\":{\"value\":0,\"unit\":\"px\"},\"left\":{\"value\":0,\"unit\":\"px\"},\"right\":{\"value\":0,\"unit\":\"px\"}},\"backgroundHeight\":{\"value\":0,\"unit\":\"px\"},\"backgroundWidth\":{\"value\":0,\"unit\":\"px\"}},\"containerStyle\":{\"textAlign\":\"start\",\"widgetAlignSelf\":\"default\",\"borderStyle\":\"Solid\",\"borderRadius\":\"5\",\"borderWidth\":\"0\",\"borderLeftColor\":{\"value\":\"\",\"expression\":\"\"},\"color\":\"var(--t-text-color)\",\"fontSize\":\"16px\",\"fontFamily\":\"Gadugi\",\"fontWeight\":\"400\",\"fontStyle\":\"normal\",\"textDecoration\":\"normal\",\"backgroundRepeat\":\"no-repeat\",\"backgroundAttachment\":\"Scroll\",\"backgroundPosition\":\"center center\",\"backgroundSizeType\":\"Contain\",\"selectedImages\":[],\"opacity\":\"1\",\"heightSizingType\":\"FitToContent\",\"widthSizingType\":\"FitToContainer\",\"dimensions\":{\"width\":{\"value\":0,\"unit\":\"px\"},\"height\":{\"value\":100,\"unit\":\"px\"}},\"minDimention\":{\"width\":{\"value\":0,\"unit\":\"px\"},\"height\":{\"value\":0,\"unit\":\"px\"}},\"maxDimention\":{\"width\":{\"value\":0,\"unit\":\"px\"},\"height\":{\"value\":0,\"unit\":\"px\"}},\"minWidthActive\":false,\"maxWidthActive\":false,\"minHeightActive\":false,\"maxHeightActive\":false,\"canvasDimension\":{\"width\":\"unset\",\"height\":\"unset\"},\"widgetWidth\":\"fit-container\",\"widgetHeight\":\"fit-content\",\"orientation\":\"Inherit\",\"labelOrientationAlignment\":\"\",\"isHideOnMobile\":false,\"isHideOnTablet\":false,\"isHideOnDesktop\":false,\"shadowColor\":\"#000000\",\"elevation\":0,\"IOSShadow\":{\"shadowColor\":\"#000000\",\"shadowOffset\":{\"width\":0,\"height\":0},\"shadowOpacity\":0,\"shadowRadius\":0},\"margin\":{\"type\":{\"value\":0,\"unit\":\"px\"},\"top\":{\"value\":0,\"unit\":\"px\"},\"bottom\":{\"value\":0,\"unit\":\"px\"},\"left\":{\"value\":0,\"unit\":\"px\"},\"right\":{\"value\":0,\"unit\":\"px\"}},\"padding\":{\"type\":{\"value\":5,\"unit\":\"px\"},\"top\":{\"value\":0,\"unit\":\"px\"},\"bottom\":{\"value\":0,\"unit\":\"px\"},\"left\":{\"value\":0,\"unit\":\"px\"},\"right\":{\"value\":0,\"unit\":\"px\"}},\"backgroundHeight\":{\"value\":0,\"unit\":\"px\"},\"backgroundWidth\":{\"value\":0,\"unit\":\"px\"}},\"visibility\":{\"type\":\"Always\"},\"enablement\":{\"type\":\"Always\",\"readonlyStyle\":\"Control\"},\"imageCollectionInfo\":{},\"tooltipStyle\":{\"color\":\"#fff\",\"fontSize\":\"16px\",\"fontStyle\":\"400\",\"backgroundColor\":\"#495057\",\"textDecoration\":\"normal\"},\"orientation\":\"vertical\",\"hideSettings\":true,\"hideChildrenLabel\":false,\"hideControlAction\":{},\"droppable\":true,\"labelOrientation\":\"Vertical\",\"containerAnimation\":{\"animationName\":\"animate__none\",\"animationDelay\":0,\"animationDuration\":1000,\"isOnAppearance\":true,\"isInfinite\":false,\"animationTiming\":\"cubic-bezier(0, 0, 1, 1)\"},\"alignItems\":\"start\",\"justifyContent\":\"start\",\"parentOrientation\":\"vertical\",\"leftRegionEnabled\":false,\"rightRegionEnabled\":false,\"isLeftPanelResponsive\":false,\"isRightPanelResponsive\":false,\"leftWidthType\":\"custom\",\"leftWidth\":250,\"leftWidthUnit\":\"px\",\"rightWidthType\":\"custom\",\"rightWidth\":250,\"rightWidthUnit\":\"px\"},\"refId\":\"5b4568bf-e24d-42fa-85e8-c5e82cda8f3f\",\"containers\":[],\"parentRefId\":null,\"index\":null,\"classTypeKey\":\"Container\",\"settingsConfig\":[],\"typeName\":\"Container\",\"tag\":{\"title\":\"MainPlaceholder_container\"},\"children\":[]}]}]}",
  "PageLayoutId": null,
  "AccountCode": null,
  "ModelId": null,
  "OrientationId": null,
  "VersionNumber": 1,
  "VersionNote": null,
  "OldVersions": null,
  "LayoutId": "2c4b74b3-e742-4cb1-aef8-080221e8ef67",
  "PageLayout": null,
  "IsUnauthorizedPage": false,
  "pageTemplateId": null,
  "pageTemplate": null,
  "PagesLayout": null,
  "AnynomousPage": true,
  "IsHomePage": false,
  "IsMobile": false,
  "MobileAppId": null,
  "AppId": null,
  "TypeId": null,
  "PageContainerId": 0,
  "MaestroThemeId": "d5812dd5-cd24-415c-9ebe-4371129fd57a",
  "MaestroThemeDto": null,
  "ClonedId": "00000000-0000-0000-0000-000000000000",
  "NavigationId": [],
  "SitePortalIds": [],
  "MediaCollections": [
    {
      "ImageId": "153b8bc1-e50d-4d4c-bff1-7f8d43da4004",
      "MediaCollectionId": "bdc34a25-24bb-4e98-b85d-cc4e46db3163"
    }
  ],
  "CreatedBy": 40,
  "CreationDate": "2025-01-12T15:06:44.3289203Z",
  "ModifiedBy": 40,
  "ModificationDate": "2025-01-23T15:36:20.8893444Z",
  "DeletedBy": null,
  "DeletionDate": null,
  "MetaData": {},
  "Id": "d7f0b807-f4d4-41ec-8491-69f6b35996b4",
  "Name": "Page_APPLICATIONS"
}